{
  "id": "log_large",
  "name": "Large Log",
  "type": "mine",
  "specs": {
    "texture": {
      "name": "mines",
      "x": 32,
      "y": 156,
      "width": 32,
      "height": 32
    },
    "drop": [
      {
        "id": "wood",
        "chance": [
          100,
          100
        ],
        "amount": [
          2,
          3
        ]
      }
    ],
    "ground_collision": {
      "width": 32,
      "height": 32,
      "x": 0,
      "y": 0
    },
    "action_collision": {
      "width": 36,
      "height": 36,
      "x": -2,
      "y": -2
    },
    "action": "cut_tree"
  }
}