{
  "id": "radioactive_node",
  "name": "Radioactive ore",
  "type": "mine",
  "specs": {
    "exp": 18,
    "texture": {
      "name": "mines",
      "x": 244,
      "y": 2,
      "width": 16,
      "height": 16
    },
    "drop": [
      {
        "id": "radioactive_ore",
        "amount": 1,
        "chance": 100
      }
    ],
    "action": "mine",
    "ground_collision": {
      "width": 16,
      "height": 16,
      "x": 0,
      "y": 0
    },
    "action_collision": {
      "width": 20,
      "height": 20,
      "x": -2,
      "y": -2
    }
  }
}